qstr/__init__.py
qstr/version.py
qstr-0.0.1.dist-info/METADATA
qstr-0.0.1.dist-info/WHEEL
qstr-0.0.1.dist-info/top_level.txt
qstr-0.0.1.dist-info/RECORD
