Metadata-Version: 2.1
Name: qstr
Version: 0.0.1
Summary: qstr
Home-page: http://github.com/zhiqingxiao/qstr/
Author: Zhiqing Xiao
Author-email: xzq.xiaozhiqing@gmail.com
Classifier: Programming Language :: Python
Classifier: Intended Audience :: Science/Research
